README.md
setup.cfg
setup.py
GISterical.egg-info/PKG-INFO
GISterical.egg-info/SOURCES.txt
GISterical.egg-info/dependency_links.txt
GISterical.egg-info/entry_points.txt
GISterical.egg-info/requires.txt
GISterical.egg-info/top_level.txt
src/gisterical/__init__.py
src/gisterical/main.py
src/gisterical/core/__init__.py
src/gisterical/core/create_folder_structure.py
src/gisterical/core/get_faces.py
src/gisterical/core/image_metadata.py
src/gisterical/core/image_paths.py
src/gisterical/data/__init__.py
src/gisterical/data/countries.geojson
src/gisterical/data/worldcities.csv
src/gisterical/database/__init__.py
src/gisterical/database/db_api.py
src/gisterical/database/schema.py
src/gisterical/settings/__init__.py
src/gisterical/settings/settings.json
src/gisterical/settings/settings.py
src/gisterical/util/__init__.py
src/gisterical/util/decorators.py
src/gisterical/util/file_meta.py