Metadata-Version: 2.1
Name: GISterical
Version: 0.5.9
Summary: UNKNOWN
Home-page: https://github.com/pavelcherepan/gisterical
Author: Pavel Cherepanskiy
Author-email: pavelcherepansky@gmail.com
License: MIT
Keywords: example project
Platform: UNKNOWN
Classifier: Programming Language :: Python :: 3.9
Classifier: Programming Language :: Python :: 3.10
Classifier: Programming Language :: Python :: 3 :: Only
Requires-Python: >=3.9, <4
